get_args/__init__.py
get_args/get_args.yml
get_args/getargs.py
get_args/main.py
get_args-1.3.dist-info/LICENSE
get_args-1.3.dist-info/METADATA
get_args-1.3.dist-info/WHEEL
get_args-1.3.dist-info/entry_points.txt
get_args-1.3.dist-info/top_level.txt
get_args-1.3.dist-info/RECORD
