Metadata-Version: 2.1
Name: get-args
Version: 1.3
Summary: get args from command line, environment and configuration file.
Home-page: https://github.com/fun04wr0ng/get_args
Author: fun04wr0ng
Author-email: fun04wr0ng@gmail.com
License: GPL v3+
Platform: UNKNOWN
Classifier: Programming Language :: Python :: 3.6
Classifier: License :: OSI Approved :: GNU General Public License v3 or later (GPLv3+)
Classifier: Operating System :: POSIX :: Linux
Requires-Python: >=3.6
Requires-Dist: python-dotenv
Requires-Dist: pyyaml (>=5.1)
Provides-Extra: toml
Requires-Dist: toml ; extra == 'toml'
